griddot/__init__.py
griddot/cli.py
griddot/provision_keycloak/__init__.py
griddot/provision_keycloak/main.py
griddot/tools/__init__.py
griddot/tools/deploy.py
griddot/tools/secrets.py
griddot/tools/utils.py
griddot-0.2.1.dist-info/METADATA
griddot-0.2.1.dist-info/WHEEL
griddot-0.2.1.dist-info/entry_points.txt
griddot-0.2.1.dist-info/RECORD
