Metadata-Version: 2.4
Name: griddot
Version: 0.2.1
Summary: Griddot packages
Author-email: Griddot <info@griddot.net>
Classifier: Intended Audience :: Developers
Classifier: Natural Language :: English
Requires-Python: >=3.12
Requires-Dist: click
Requires-Dist: cryptography
Requires-Dist: pyyaml
Requires-Dist: requests>=2.32.3
Provides-Extra: dev
Requires-Dist: pytest; extra == 'dev'
